ebike_dl/main.py
ebike_dl-0.3.3.dist-info/entry_points.txt
ebike_dl-0.3.3.dist-info/WHEEL
ebike_dl-0.3.3.dist-info/METADATA
ebike_dl-0.3.3.dist-info/RECORD
