Metadata-Version: 2.1
Name: ebike-dl
Version: 0.3.3
Summary: Bosch eBike Connect Activity Downloader
Home-page: https://github.com/eMerzh/ebike-dl
License: MIT
Author: Brice Maron
Author-email: bmaron@gmail.com
Requires-Python: >=3.10,<4.0
Classifier: License :: OSI Approved :: MIT License
Classifier: Programming Language :: Python :: 3
Classifier: Programming Language :: Python :: 3.10
Requires-Dist: requests (>=2.28.1,<3.0.0)
Requires-Dist: typer (>=0.6.1,<0.7.0)
